ffcmdr/__init__.py
ffcmdr/arg.py
ffcmdr/cmd.py
ffcmdr/filter_complex.py
ffcmdr/run.py
ffcmdr-0.4.0.dist-info/LICENSE
ffcmdr-0.4.0.dist-info/METADATA
ffcmdr-0.4.0.dist-info/WHEEL
ffcmdr-0.4.0.dist-info/RECORD
